{
    "Variables":  {
                      "Global-RunbookWorkerAccessCredentialName":  {
                                                                       "isEncrypted":  false,
                                                                       "Description":  "",
                                                                       "Value":  "Automation@scorchdev.com"
                                                                   },
                      "Global-SubscriptionName":  {
                                                      "isEncrypted":  false,
                                                      "Description":  "",
                                                      "Value":  "Visual Studio Enterprise with MSDN"
                                                  },
                      "Global-ResourceGroupName":  {
                                                       "isEncrypted":  false,
                                                       "Description":  "",
                                                       "Value":  "SCOrchDev"
                                                   },
                      "Global-AutomationAccountName":  {
                                                           "isEncrypted":  false,
                                                           "Description":  "",
                                                           "Value":  "SCOrchDev"
                                                       },
                      "Global-SubscriptionAccessCredentialName":  {
                                                                      "isEncrypted":  false,
                                                                      "Description":  "",
                                                                      "Value":  "Automation@scorchdev.com"
                                                                  },
                      "Global-HybridRunbookWorker":  {
                                                         "isEncrypted":  false,
                                                         "Description":  "",
                                                         "Value":  "{\"USEast\":[\"omsa1.scorchdev.com\",\"omsa2.scorchdev.com\"]}"
                                                     }
                  }
}
